{
  "config": {
    "forbidOnly": false,
    "fullyParallel": false,
    "globalSetup": null,
    "globalTeardown": null,
    "globalTimeout": 0,
    "grep": {},
    "grepInvert": null,
    "maxFailures": 0,
    "metadata": {},
    "preserveOutput": "always",
    "projects": [
      {
        "outputDir": "C:/Users/eliza.szilagyi/Desktop/Projects/Playwright/Playwright with Typescript/Playwright_tests_with_Typescript/test-results",
        "repeatEach": 1,
        "retries": 0,
        "id": "",
        "name": "",
        "testDir": "C:/Users/eliza.szilagyi/Desktop/Projects/Playwright/Playwright with Typescript/Playwright_tests_with_Typescript",
        "testIgnore": [],
        "testMatch": [
          "pomTests/loginTests.test.ts"
        ],
        "timeout": 30000
      }
    ],
    "reporter": [
      [
        "dot",
        null
      ],
      [
        "json",
        {
          "outputFile": "jsonReports/jsonReport.json"
        }
      ],
      [
        "html",
        {
          "open": "always"
        }
      ]
    ],
    "reportSlowTests": {
      "max": 5,
      "threshold": 15000
    },
    "configFile": "C:\\Users\\eliza.szilagyi\\Desktop\\Projects\\Playwright\\Playwright with Typescript\\Playwright_tests_with_Typescript\\playwright.config.ts",
    "rootDir": "C:/Users/eliza.szilagyi/Desktop/Projects/Playwright/Playwright with Typescript/Playwright_tests_with_Typescript",
    "quiet": false,
    "shard": null,
    "updateSnapshots": "missing",
    "version": "1.29.1",
    "workers": 4,
    "webServer": null
  },
  "suites": [
    {
      "title": "pomTests\\loginTests.test.ts",
      "file": "pomTests/loginTests.test.ts",
      "column": 0,
      "line": 0,
      "specs": [],
      "suites": [
        {
          "title": "Login tests",
          "file": "pomTests/loginTests.test.ts",
          "line": 7,
          "column": 6,
          "specs": [
            {
              "title": "Login | test_01",
              "ok": true,
              "tags": [],
              "tests": [
                {
                  "timeout": 30000,
                  "annotations": [],
                  "expectedStatus": "passed",
                  "projectId": "",
                  "projectName": "",
                  "results": [
                    {
                      "workerIndex": 0,
                      "status": "passed",
                      "duration": 14242,
                      "errors": [],
                      "stdout": [],
                      "stderr": [],
                      "retry": 0,
                      "startTime": "2023-02-09T14:12:51.065Z",
                      "attachments": [
                        {
                          "name": "screenshot",
                          "contentType": "image/png",
                          "path": "C:\\Users\\eliza.szilagyi\\Desktop\\Projects\\Playwright\\Playwright with Typescript\\Playwright_tests_with_Typescript\\test-results\\pomTests-loginTests-Login-tests-Login-test-01\\test-finished-1.png"
                        }
                      ]
                    }
                  ],
                  "status": "expected"
                }
              ],
              "id": "e181bc1647c43da81fa0-ba1a76e041f8aa393082",
              "file": "pomTests/loginTests.test.ts",
              "line": 8,
              "column": 9
            },
            {
              "title": "Login with invalid email | test_02",
              "ok": true,
              "tags": [],
              "tests": [
                {
                  "timeout": 30000,
                  "annotations": [],
                  "expectedStatus": "passed",
                  "projectId": "",
                  "projectName": "",
                  "results": [
                    {
                      "workerIndex": 0,
                      "status": "passed",
                      "duration": 13385,
                      "errors": [],
                      "stdout": [],
                      "stderr": [],
                      "retry": 0,
                      "startTime": "2023-02-09T14:13:06.270Z",
                      "attachments": [
                        {
                          "name": "screenshot",
                          "contentType": "image/png",
                          "path": "C:\\Users\\eliza.szilagyi\\Desktop\\Projects\\Playwright\\Playwright with Typescript\\Playwright_tests_with_Typescript\\test-results\\pomTests-loginTests-Login-tests-Login-with-invalid-email-test-02\\test-finished-1.png"
                        }
                      ]
                    }
                  ],
                  "status": "expected"
                }
              ],
              "id": "e181bc1647c43da81fa0-93dd64723fd4c46a24c7",
              "file": "pomTests/loginTests.test.ts",
              "line": 16,
              "column": 9
            },
            {
              "title": "Check page elements | test_03",
              "ok": true,
              "tags": [],
              "tests": [
                {
                  "timeout": 30000,
                  "annotations": [],
                  "expectedStatus": "passed",
                  "projectId": "",
                  "projectName": "",
                  "results": [
                    {
                      "workerIndex": 0,
                      "status": "passed",
                      "duration": 7625,
                      "errors": [],
                      "stdout": [],
                      "stderr": [],
                      "retry": 0,
                      "startTime": "2023-02-09T14:13:19.658Z",
                      "attachments": [
                        {
                          "name": "screenshot",
                          "contentType": "image/png",
                          "path": "C:\\Users\\eliza.szilagyi\\Desktop\\Projects\\Playwright\\Playwright with Typescript\\Playwright_tests_with_Typescript\\test-results\\pomTests-loginTests-Login-tests-Check-page-elements-test-03\\test-finished-1.png"
                        }
                      ]
                    }
                  ],
                  "status": "expected"
                }
              ],
              "id": "e181bc1647c43da81fa0-d3f60f066689057465d8",
              "file": "pomTests/loginTests.test.ts",
              "line": 25,
              "column": 9
            },
            {
              "title": "Login with invalid password | test_02",
              "ok": true,
              "tags": [],
              "tests": [
                {
                  "timeout": 30000,
                  "annotations": [],
                  "expectedStatus": "passed",
                  "projectId": "",
                  "projectName": "",
                  "results": [
                    {
                      "workerIndex": 0,
                      "status": "passed",
                      "duration": 13257,
                      "errors": [],
                      "stdout": [],
                      "stderr": [],
                      "retry": 0,
                      "startTime": "2023-02-09T14:13:27.286Z",
                      "attachments": [
                        {
                          "name": "screenshot",
                          "contentType": "image/png",
                          "path": "C:\\Users\\eliza.szilagyi\\Desktop\\Projects\\Playwright\\Playwright with Typescript\\Playwright_tests_with_Typescript\\test-results\\pomTests-loginTests-Login-tests-Login-with-invalid-password-test-02\\test-finished-1.png"
                        }
                      ]
                    }
                  ],
                  "status": "expected"
                }
              ],
              "id": "e181bc1647c43da81fa0-4bea6fece3f48c8ae37f",
              "file": "pomTests/loginTests.test.ts",
              "line": 32,
              "column": 9
            }
          ]
        }
      ]
    }
  ],
  "errors": []
}